{"SubTexture":[{"width":176,"y":1677,"height":134,"name":"mine-lights","x":1},{"width":114,"y":1813,"height":158,"name":"gold-leaf","x":106},{"width":151,"y":1511,"height":164,"name":"portal-city","x":1},{"width":47,"y":1756,"height":75,"name":"portal-on","x":222},{"width":58,"y":1973,"height":53,"name":"light-portal","x":106},{"width":143,"y":1511,"height":131,"name":"dragon-cross-larg","x":154},{"width":53,"y":1973,"height":41,"name":"light-dragon-cross-wins","x":166},{"width":900,"y":1,"height":1508,"name":"main-map","x":1},{"width":103,"y":1813,"height":217,"name":"top-montain","x":1},{"width":86,"y":1644,"height":110,"name":"portal-tower","x":179}],"width":1024,"imagePath":"main-map_tex.png","height":2048,"name":"main-map"}