{"SubTexture":[{"width":560,"y":558,"height":325,"name":"asset_castle","x":1},{"width":566,"y":228,"height":328,"name":"syb_CastleBroken","x":1},{"width":981,"y":1,"height":225,"name":"asset_banner","x":1},{"width":119,"y":686,"height":133,"name":"asset_defeat_D","x":720},{"width":93,"y":821,"height":129,"name":"asset_defeat_T","x":679},{"width":87,"y":885,"height":123,"name":"asset_defeat_E1","x":198},{"width":106,"y":820,"height":123,"name":"asset_defeat_A","x":841},{"width":68,"y":885,"height":119,"name":"asset_defeat_F","x":372},{"width":72,"y":820,"height":119,"name":"asset_defeat_E2","x":949},{"width":155,"y":558,"height":155,"name":"asset_glow_white","x":563},{"width":130,"y":558,"height":126,"name":"asset_star_middle","x":720},{"width":102,"y":885,"height":105,"name":"asset_star_side","x":94},{"width":123,"y":558,"height":132,"name":"asset_V","x":852},{"width":114,"y":715,"height":132,"name":"asset_Y","x":563},{"width":93,"y":849,"height":124,"name":"asset_I","x":563},{"width":113,"y":692,"height":126,"name":"asset_R","x":841},{"width":83,"y":885,"height":121,"name":"asset_C","x":287},{"width":91,"y":885,"height":121,"name":"asset_O","x":1},{"width":67,"y":692,"height":116,"name":"asset_T","x":956}],"width":1024,"height":1024,"name":"battle-outcome-mc","imagePath":"battle-outcome-mc_tex.png"}